butter/__init__.py
butter/butter.py
butter_dev-0.0.1.dist-info/METADATA
butter_dev-0.0.1.dist-info/WHEEL
butter_dev-0.0.1.dist-info/licenses/LICENSE
butter_dev-0.0.1.dist-info/RECORD
