Metadata-Version: 2.4
Name: butter-dev
Version: 0.0.1
Summary: butter
Author-email: Erik Dunteman <erik@butter.dev>
License-File: LICENSE
Requires-Python: >=3.7
Provides-Extra: dev
Requires-Dist: build; extra == 'dev'
Requires-Dist: ruff>=0.3.0; extra == 'dev'
Requires-Dist: twine; extra == 'dev'
